{
  "Article": [
    {
      "Title": "jjjjjjjjjjjjjjjjjjjjjjjjjjjjjj",
      "contenu": "kjj",
      "Author": "j",
      "Date": "2022-05-14",
      "id": 4
    },
    {
      "Title": "re",
      "contenu": "ds",
      "Author": "dd",
      "Date": "",
      "id": 6
    }
  ],
  "users": [
    {
      "firstname": "rakia",
      "lastname": "felly",
      "username": "cvb",
      "password": "xcv",
      "id": 1
    },
    {
      "firstname": "rakia",
      "lastname": "felly",
      "username": "aze",
      "password": "aze",
      "id": 2
    }
  ]
}